{"images":{"id":"100898","file_name":"R03_U05_C12_20220730_022151.jpg","height":"1920","width":"1080","date_captured":"2022-07-30 07:11:02","file_size":"866978","collection_method":"스마트폰","daynight":"오전","place":"서울","course":"C12","gps":"37.525269972222,126.92731397222","speed":"15.4","altitude":"42.184","id_code":"U05","weather":"맑음","make":"samsung","model_name":"SM-G981N","bike_lane":"R03","boundingcount":"7"},"annotations":[{"drawing":"bbox","category_id":"E02N","category_name":"주변환경","sub_category_name":"횡단보도","state_name":"해당없음","segmentation":[],"bbox":[488.7931,293.592224,591.2069,964.6602]},{"drawing":"bbox","category_id":"C05N","category_name":"이동주체","sub_category_name":"자전거","state_name":"해당없음","segmentation":[],"bbox":[274.3028,108.699554,128.007965,118.385651]},{"drawing":"bbox","category_id":"C01N","category_name":"이동주체","sub_category_name":"자동차(불법주정차)","state_name":"해당없음","segmentation":[],"bbox":[69.1265,78.10169,79.6988,65.89831]},{"drawing":"bbox","category_id":"D01T","category_name":"도로시설","sub_category_name":"볼라드","state_name":"정상","segmentation":[],"bbox":[884.8193,126.915253,34.1566162,134.2373]},{"drawing":"polygon","category_id":"A01N","category_name":"도로재질","sub_category_name":"포장도로","state_name":"해당없음","segmentation":[150.758133,188.490189,20.7942257,218.3886,0,232.687851,33.7906075,245.68718,246.931381,274.285736,0,508.273621,0,1920,1080,1920,947.929,1244.48389,466.508881,274.894562,289.704132,257.846832,129.940826,242.930084,72.42603,232.275253,83.07692,225.882355],"bbox":[0,188.490189,1080,1731.50977]},{"drawing":"bbox","category_id":"D02T","category_name":"도로시설","sub_category_name":"분리봉","state_name":"정상","segmentation":[],"bbox":[233.444183,117.167038,41.0451355,81.24722]},{"drawing":"bbox","category_id":"D02T","category_name":"도로시설","sub_category_name":"분리봉","state_name":"정상","segmentation":[],"bbox":[679.81,74.40534,47.8859863,106.904228]}]}